init_paper/__init__.py
init_paper/__main__.py
init_paper/choice_option.py
init_paper/main.py
init_paper-0.1.1.dist-info/METADATA
init_paper-0.1.1.dist-info/WHEEL
init_paper-0.1.1.dist-info/entry_points.txt
init_paper-0.1.1.dist-info/RECORD
